upload_component/UploadComponent.py
upload_component/UploadComponent_original.py
upload_component/__init__.py
upload_component/_imports_.py
upload_component/metadata.json
upload_component/package-info.json
upload_component/upload_component.min.js
upload_component/upload_component.min.js.map
upload_component-0.0.5.dist-info/LICENSE
upload_component-0.0.5.dist-info/METADATA
upload_component-0.0.5.dist-info/WHEEL
upload_component-0.0.5.dist-info/top_level.txt
upload_component-0.0.5.dist-info/RECORD
