Metadata-Version: 2.1
Name: upload-component
Version: 0.0.5
Summary: Project Description
Author: Ujwala <ujwalaguttikonda@gmail.com>
License: MIT
Classifier: Framework :: Dash
License-File: LICENSE
